{
  "generated_at": "2025-08-12T15:37:34.715382+00:00",
  "timeframe": "1m",
  "breakout_len": 20,
  "min_pct_move": 5.0,
  "min_rsi_mom": 50.0,
  "buy_logic": {
    "buy_rsi_max": 65.0,
    "buy_delta_min": 0.5,
    "near_breakout_pct": 0.3
  },
  "ki": {
    "scorer_url_set": false,
    "min_score": 65
  },
  "signals": [
    {
      "symbol": "DDD",
      "price": 2.26,
      "rsi": 31.37,
      "pct_move": -0.22,
      "prev_high_n": 20,
      "prev_high_value": 2.3777,
      "near_breakout_pct": 0.3,
      "breakout": false,
      "momentum": false,
      "recommendation": "HOLD",
      "qty": 0,
      "ki_score": null,
      "ki_pass": true,
      "timestamp": "2025-08-12T15:37:24.805204+00:00",
      "spark": [
        2.27,
        2.275,
        2.295,
        2.289,
        2.355,
        2.33,
        2.355,
        2.35,
        2.365,
        2.3799,
        2.378,
        2.38,
        2.3777,
        2.39,
        2.39,
        2.3909,
        2.371,
        2.3984,
        2.3899,
        2.37,
        2.37,
        2.37,
        2.3708,
        2.35,
        2.3517,
        2.34,
        2.34,
        2.345,
        2.37,
        2.355,
        2.345,
        2.345,
        2.34,
        2.33,
        2.315,
        2.311,
        2.3,
        2.2945,
        2.29,
        2.295,
        2.32,
        2.295,
        2.2898,
        2.285,
        2.285,
        2.27,
        2.265,
        2.26,
        2.265,
        2.26
      ],
      "sl_percent": null,
      "tp_percent": null,
      "trailing_percent": null,
      "sl_price": null,
      "tp_price": null,
      "qty_sized": null
    },
    {
      "symbol": "ZIP",
      "price": 3.725,
      "rsi": 47.73,
      "pct_move": 0.0,
      "prev_high_n": 20,
      "prev_high_value": 3.75,
      "near_breakout_pct": 0.3,
      "breakout": false,
      "momentum": false,
      "recommendation": "HOLD",
      "qty": 0,
      "ki_score": null,
      "ki_pass": true,
      "timestamp": "2025-08-12T15:37:25.147937+00:00",
      "spark": [
        3.745,
        3.77,
        3.78,
        3.765,
        3.7708,
        3.77,
        3.77,
        3.755,
        3.73,
        3.715,
        3.715,
        3.71,
        3.705,
        3.685,
        3.765,
        3.76,
        3.75,
        3.74,
        3.75,
        3.74,
        3.74,
        3.74,
        3.745,
        3.73,
        3.725,
        3.71,
        3.705,
        3.72,
        3.735,
        3.75,
        3.74,
        3.745,
        3.73,
        3.72,
        3.72,
        3.725,
        3.735,
        3.73,
        3.735,
        3.735,
        3.735,
        3.735,
        3.735,
        3.73,
        3.705,
        3.705,
        3.705,
        3.73,
        3.725,
        3.725
      ],
      "sl_percent": null,
      "tp_percent": null,
      "trailing_percent": null,
      "sl_price": null,
      "tp_price": null,
      "qty_sized": null
    },
    {
      "symbol": "MSOS",
      "price": 4.615,
      "rsi": 41.62,
      "pct_move": 0.0,
      "prev_high_n": 20,
      "prev_high_value": 4.68,
      "near_breakout_pct": 0.3,
      "breakout": false,
      "momentum": false,
      "recommendation": "HOLD",
      "qty": 0,
      "ki_score": null,
      "ki_pass": true,
      "timestamp": "2025-08-12T15:37:25.458876+00:00",
      "spark": [
        4.555,
        4.6148,
        4.6201,
        4.6713,
        4.695,
        4.645,
        4.64,
        4.6346,
        4.635,
        4.6435,
        4.6501,
        4.6599,
        4.6401,
        4.6301,
        4.6384,
        4.66,
        4.6714,
        4.6554,
        4.66,
        4.6846,
        4.68,
        4.6945,
        4.71,
        4.7,
        4.6999,
        4.695,
        4.6799,
        4.6675,
        4.65,
        4.655,
        4.645,
        4.665,
        4.665,
        4.655,
        4.65,
        4.675,
        4.655,
        4.6481,
        4.6299,
        4.635,
        4.635,
        4.6215,
        4.625,
        4.615,
        4.605,
        4.625,
        4.615,
        4.615,
        4.615,
        4.615
      ],
      "sl_percent": null,
      "tp_percent": null,
      "trailing_percent": null,
      "sl_price": null,
      "tp_price": null,
      "qty_sized": null
    },
    {
      "symbol": "LDI",
      "price": 1.895,
      "rsi": 79.74,
      "pct_move": 0.27,
      "prev_high_n": 20,
      "prev_high_value": 1.89,
      "near_breakout_pct": 0.3,
      "breakout": true,
      "momentum": true,
      "recommendation": "BUY",
      "qty": 10,
      "ki_score": 85,
      "ki_pass": true,
      "timestamp": "2025-08-12T15:37:26.832993+00:00",
      "spark": [
        1.81,
        1.815,
        1.815,
        1.82,
        1.83,
        1.835,
        1.8307,
        1.83,
        1.83,
        1.84,
        1.835,
        1.84,
        1.85,
        1.84,
        1.835,
        1.84,
        1.84,
        1.845,
        1.84,
        1.845,
        1.845,
        1.84,
        1.845,
        1.8492,
        1.845,
        1.845,
        1.845,
        1.835,
        1.835,
        1.835,
        1.84,
        1.849,
        1.855,
        1.855,
        1.855,
        1.85,
        1.855,
        1.855,
        1.86,
        1.855,
        1.8591,
        1.855,
        1.86,
        1.865,
        1.865,
        1.8652,
        1.865,
        1.865,
        1.8899,
        1.895
      ],
      "sl_percent": 9,
      "tp_percent": 25,
      "trailing_percent": 6,
      "sl_price": 1.7245,
      "tp_price": 2.3688,
      "qty_sized": 586,
      "equity_used": 10000,
      "risk_pct_used": 1,
      "ki_min": 65,
      "rationale": "Das Setup zeigt starkes Momentum und einen best\u00e4tigten Breakout, jedoch ist der RSI bereits hoch."
    },
    {
      "symbol": "GETY",
      "price": 1.6654,
      "rsi": 50.29,
      "pct_move": 0.02,
      "prev_high_n": 20,
      "prev_high_value": 1.675,
      "near_breakout_pct": 0.3,
      "breakout": false,
      "momentum": true,
      "recommendation": "HOLD",
      "qty": 0,
      "ki_score": null,
      "ki_pass": true,
      "timestamp": "2025-08-12T15:37:28.678691+00:00",
      "spark": [
        1.685,
        1.6808,
        1.685,
        1.6817,
        1.6818,
        1.6857,
        1.695,
        1.691,
        1.695,
        1.69,
        1.685,
        1.67,
        1.66,
        1.65,
        1.6465,
        1.64,
        1.6436,
        1.64,
        1.64,
        1.64,
        1.64,
        1.64,
        1.6489,
        1.65,
        1.655,
        1.66,
        1.6594,
        1.655,
        1.66,
        1.6637,
        1.6654,
        1.66,
        1.66,
        1.665,
        1.6691,
        1.665,
        1.6601,
        1.66,
        1.665,
        1.66,
        1.6608,
        1.675,
        1.675,
        1.675,
        1.675,
        1.675,
        1.665,
        1.665,
        1.665,
        1.6654
      ],
      "sl_percent": null,
      "tp_percent": null,
      "trailing_percent": null,
      "sl_price": null,
      "tp_price": null,
      "qty_sized": null
    },
    {
      "symbol": "AGL",
      "price": 0.8506,
      "rsi": 33.25,
      "pct_move": 0.0,
      "prev_high_n": 20,
      "prev_high_value": 0.8716,
      "near_breakout_pct": 0.3,
      "breakout": false,
      "momentum": false,
      "recommendation": "HOLD",
      "qty": 0,
      "ki_score": null,
      "ki_pass": true,
      "timestamp": "2025-08-12T15:37:29.079697+00:00",
      "spark": [
        0.8585,
        0.857,
        0.8494,
        0.849699,
        0.8508,
        0.85475,
        0.8508,
        0.8517,
        0.8421,
        0.8449,
        0.8494,
        0.8501,
        0.85,
        0.86,
        0.8668,
        0.8669,
        0.867,
        0.8628,
        0.87,
        0.8688,
        0.8664,
        0.8667,
        0.86465,
        0.8659,
        0.8616,
        0.871,
        0.87,
        0.8699,
        0.8716,
        0.87155,
        0.8673,
        0.86895,
        0.87116,
        0.8699,
        0.8714,
        0.8715,
        0.8675,
        0.8697,
        0.8681,
        0.8686,
        0.8602,
        0.8582,
        0.8581,
        0.8514,
        0.8511,
        0.85,
        0.8514,
        0.8525,
        0.8506,
        0.8506
      ],
      "sl_percent": null,
      "tp_percent": null,
      "trailing_percent": null,
      "sl_price": null,
      "tp_price": null,
      "qty_sized": null
    },
    {
      "symbol": "AMC",
      "price": 3.015,
      "rsi": 41.18,
      "pct_move": 0.17,
      "prev_high_n": 20,
      "prev_high_value": 3.07,
      "near_breakout_pct": 0.3,
      "breakout": false,
      "momentum": false,
      "recommendation": "HOLD",
      "qty": 0,
      "ki_score": null,
      "ki_pass": true,
      "timestamp": "2025-08-12T15:37:29.416647+00:00",
      "spark": [
        3.0855,
        3.115,
        3.0807,
        3.1,
        3.095,
        3.095,
        3.0821,
        3.075,
        3.06,
        3.0555,
        3.0584,
        3.055,
        3.055,
        3.0546,
        3.06,
        3.055,
        3.055,
        3.055,
        3.065,
        3.0699,
        3.065,
        3.0772,
        3.0674,
        3.06,
        3.06,
        3.07,
        3.065,
        3.0602,
        3.07,
        3.065,
        3.06,
        3.06,
        3.035,
        3.035,
        3.0199,
        3.0159,
        3.0182,
        3.015,
        3.01,
        3.0199,
        3.015,
        3.0113,
        3.015,
        3.014,
        3.0199,
        3.015,
        3.0146,
        3.02,
        3.01,
        3.015
      ],
      "sl_percent": null,
      "tp_percent": null,
      "trailing_percent": null,
      "sl_price": null,
      "tp_price": null,
      "qty_sized": null
    },
    {
      "symbol": "LAC",
      "price": 2.915,
      "rsi": 60.97,
      "pct_move": -0.1,
      "prev_high_n": 20,
      "prev_high_value": 2.92,
      "near_breakout_pct": 0.3,
      "breakout": true,
      "momentum": true,
      "recommendation": "BUY",
      "qty": 10,
      "ki_score": 85,
      "ki_pass": true,
      "timestamp": "2025-08-12T15:37:31.039883+00:00",
      "spark": [
        2.855,
        2.8699,
        2.865,
        2.865,
        2.8684,
        2.8697,
        2.865,
        2.865,
        2.86,
        2.87,
        2.865,
        2.8698,
        2.8689,
        2.87,
        2.8737,
        2.88,
        2.8728,
        2.8753,
        2.8763,
        2.875,
        2.875,
        2.875,
        2.8863,
        2.88,
        2.88,
        2.8797,
        2.885,
        2.8838,
        2.885,
        2.895,
        2.8835,
        2.8999,
        2.9,
        2.89,
        2.897,
        2.899,
        2.905,
        2.905,
        2.91,
        2.915,
        2.905,
        2.909,
        2.915,
        2.915,
        2.92,
        2.9199,
        2.915,
        2.915,
        2.918,
        2.915
      ],
      "sl_percent": 9,
      "tp_percent": 25,
      "trailing_percent": 6,
      "sl_price": 2.6527,
      "tp_price": 3.6438,
      "qty_sized": 381,
      "equity_used": 10000,
      "risk_pct_used": 1,
      "ki_min": 65,
      "rationale": "Das Setup zeigt starken Momentum und einen best\u00e4tigten Breakout, was eine Kaufgelegenheit signalisiert."
    },
    {
      "symbol": "NIO",
      "price": 4.53,
      "rsi": 43.65,
      "pct_move": 0.0,
      "prev_high_n": 20,
      "prev_high_value": 4.55,
      "near_breakout_pct": 0.3,
      "breakout": false,
      "momentum": false,
      "recommendation": "HOLD",
      "qty": 0,
      "ki_score": null,
      "ki_pass": true,
      "timestamp": "2025-08-12T15:37:32.666895+00:00",
      "spark": [
        4.51,
        4.515,
        4.51,
        4.515,
        4.5128,
        4.5156,
        4.518,
        4.5199,
        4.515,
        4.515,
        4.52,
        4.515,
        4.5399,
        4.54,
        4.54,
        4.555,
        4.5551,
        4.5599,
        4.57,
        4.56,
        4.5653,
        4.5615,
        4.56,
        4.57,
        4.57,
        4.5598,
        4.559,
        4.5606,
        4.5454,
        4.545,
        4.55,
        4.545,
        4.5499,
        4.545,
        4.545,
        4.54,
        4.545,
        4.545,
        4.545,
        4.5398,
        4.54,
        4.535,
        4.54,
        4.5346,
        4.54,
        4.52,
        4.52,
        4.525,
        4.5298,
        4.53
      ],
      "sl_percent": null,
      "tp_percent": null,
      "trailing_percent": null,
      "sl_price": null,
      "tp_price": null,
      "qty_sized": null
    },
    {
      "symbol": "LAR",
      "price": 3.635,
      "rsi": 60.93,
      "pct_move": 0.0,
      "prev_high_n": 20,
      "prev_high_value": 3.64,
      "near_breakout_pct": 0.3,
      "breakout": true,
      "momentum": true,
      "recommendation": "BUY",
      "qty": 10,
      "ki_score": 85,
      "ki_pass": true,
      "timestamp": "2025-08-12T15:37:32.954209+00:00",
      "spark": [
        3.625,
        3.625,
        3.62,
        3.61,
        3.615,
        3.625,
        3.625,
        3.62,
        3.625,
        3.615,
        3.61,
        3.615,
        3.61,
        3.61,
        3.6012,
        3.605,
        3.595,
        3.5912,
        3.575,
        3.5849,
        3.6,
        3.6091,
        3.605,
        3.585,
        3.5828,
        3.5901,
        3.595,
        3.5951,
        3.5975,
        3.6,
        3.6,
        3.61,
        3.585,
        3.575,
        3.5801,
        3.585,
        3.585,
        3.5817,
        3.6,
        3.5911,
        3.625,
        3.6353,
        3.615,
        3.615,
        3.625,
        3.6368,
        3.635,
        3.635,
        3.635,
        3.635
      ],
      "sl_percent": 9,
      "tp_percent": 25,
      "trailing_percent": 6,
      "sl_price": 3.3079,
      "tp_price": 4.5437,
      "qty_sized": 305,
      "equity_used": 10000,
      "risk_pct_used": 1,
      "ki_min": 65,
      "rationale": "Das Setup zeigt starke Breakout- und Momentum-Signale bei einem positiven RSI, was eine Kaufempfehlung unterst\u00fctzt."
    },
    {
      "symbol": "ETHD",
      "price": 3.92,
      "rsi": 40.94,
      "pct_move": 0.24,
      "prev_high_n": 20,
      "prev_high_value": 3.96,
      "near_breakout_pct": 0.3,
      "breakout": false,
      "momentum": false,
      "recommendation": "HOLD",
      "qty": 0,
      "ki_score": null,
      "ki_pass": true,
      "timestamp": "2025-08-12T15:37:34.592945+00:00",
      "spark": [
        3.99,
        3.98,
        3.985,
        3.965,
        3.96,
        3.9599,
        3.96,
        3.975,
        3.9789,
        3.9791,
        3.975,
        3.975,
        3.96,
        3.965,
        3.96,
        3.95,
        3.9499,
        3.93,
        3.94,
        3.96,
        3.97,
        3.9601,
        3.95,
        3.96,
        3.9691,
        3.9699,
        3.9657,
        3.97,
        3.955,
        3.96,
        3.96,
        3.9563,
        3.9599,
        3.9504,
        3.955,
        3.95,
        3.945,
        3.945,
        3.936,
        3.9401,
        3.945,
        3.9391,
        3.9391,
        3.955,
        3.93,
        3.92,
        3.9,
        3.9098,
        3.9107,
        3.92
      ],
      "sl_percent": null,
      "tp_percent": null,
      "trailing_percent": null,
      "sl_price": null,
      "tp_price": null,
      "qty_sized": null
    }
  ]
}